meowid/__init__.py
meowid/py.typed
meowid-0.1.1.post2.dist-info/METADATA
meowid-0.1.1.post2.dist-info/WHEEL
meowid-0.1.1.post2.dist-info/top_level.txt
meowid-0.1.1.post2.dist-info/RECORD
